fw_gear_deid_inplace/__init__.py
fw_gear_deid_inplace/deid_file.py
fw_gear_deid_inplace/deid_template.py
fw_gear_deid_inplace/main.py
fw_gear_deid_inplace/parser.py
fw_gear_deid_inplace/utils.py
fw_gear_deid_inplace-1.3.1.dist-info/METADATA
fw_gear_deid_inplace-1.3.1.dist-info/WHEEL
fw_gear_deid_inplace-1.3.1.dist-info/licenses/LICENSE
fw_gear_deid_inplace-1.3.1.dist-info/RECORD
