Metadata-Version: 2.4
Name: fw-gear-deid-inplace
Version: 1.3.1
Summary: Deidentifies a file in place.
Project-URL: Repository, https://gitlab.com/flywheel-io/scientific-solutions/gears/deid-inplace
Author-email: Flywheel <support@flywheel.io>
License-Expression: MIT
License-File: LICENSE
Keywords: Flywheel,Gears
Classifier: Topic :: Scientific/Engineering
Requires-Python: ~=3.12
Requires-Dist: flywheel-gear-toolkit<0.7,>=0.6
Requires-Dist: flywheel-migration[pixel]~=13.10
Requires-Dist: flywheel-sdk~=20.3
Requires-Dist: fw-gear-deid-export~=1.8
Requires-Dist: jinja2<4,>=3
Requires-Dist: rpds-py<0.21,>=0.20.0
Requires-Dist: setuptools==80.9.0
